fabdeb/__init__.py
fabdeb/apt.py
fabdeb/daemon.py
fabdeb/ftp.py
fabdeb/image.py
fabdeb/mail.py
fabdeb/master_tasks.py
fabdeb/node.py
fabdeb/os.py
fabdeb/postgresql.py
fabdeb/python.py
fabdeb/redis.py
fabdeb/tools.py
fabdeb/webserver.py
fabdeb/confs/supervisord.conf
fabdeb/scripts/supervisor
fabdeb-0.4.0.dist-info/DESCRIPTION.rst
fabdeb-0.4.0.dist-info/METADATA
fabdeb-0.4.0.dist-info/RECORD
fabdeb-0.4.0.dist-info/WHEEL
fabdeb-0.4.0.dist-info/metadata.json
fabdeb-0.4.0.dist-info/top_level.txt
